README.txt
setup.cfg
setup.py
collective/__init__.py
collective.portlet.sitemap.egg-info/PKG-INFO
collective.portlet.sitemap.egg-info/SOURCES.txt
collective.portlet.sitemap.egg-info/dependency_links.txt
collective.portlet.sitemap.egg-info/entry_points.txt
collective.portlet.sitemap.egg-info/namespace_packages.txt
collective.portlet.sitemap.egg-info/not-zip-safe
collective.portlet.sitemap.egg-info/requires.txt
collective.portlet.sitemap.egg-info/top_level.txt
collective/portlet/__init__.py
collective/portlet/sitemap/__init__.py
collective/portlet/sitemap/configure.zcml
collective/portlet/sitemap/navigation_extended_recurse.pt
collective/portlet/sitemap/navigationextendedportlet.py
collective/portlet/sitemap/version.txt
collective/portlet/sitemap/profiles/default/metadata.xml
collective/portlet/sitemap/profiles/default/portlets.xml
collective/portlet/sitemap/tests/__init__.py
collective/portlet/sitemap/tests/base.py
collective/portlet/sitemap/tests/test_portlet.py
docs/HISTORY.txt
docs/INSTALL.txt
docs/LICENSE.GPL
docs/LICENSE.txt