Metadata-Version: 1.0
Name: collective.portlet.sitemap
Version: 1.0.4
Summary: Plone 3 and 4 navigation portlet extended
Home-page: http://plone.org
Author: Ingeniweb
Author-email: support@ingeniweb.com
License: GPL
Keywords: plone portlet navigation
Platform: UNKNOWN
Classifier: Framework :: Plone
Classifier: Framework :: Plone :: 3.3
Classifier: Framework :: Plone :: 4.0
Classifier: Framework :: Plone :: 4.1
Classifier: Programming Language :: Python
Classifier: Topic :: Software Development :: Libraries :: Python Modules
